main.py
zsh_compose/__init__.py
zsh_compose/__version__.py
zsh_compose-0.0.1.dist-info/LICENSE.txt
zsh_compose-0.0.1.dist-info/METADATA
zsh_compose-0.0.1.dist-info/RECORD
zsh_compose-0.0.1.dist-info/WHEEL
zsh_compose-0.0.1.dist-info/entry_points.txt
zsh_compose-0.0.1.dist-info/top_level.txt
