Metadata-Version: 2.1
Name: zsh-compose
Version: 0.0.1
Summary: Complete ZSH manager
Home-page: https://github.com/MaT1g3R/zsh-compose
Author: Peijun Ma
Author-email: peijun.ma@protonmail.com
License: Apache 2.0
Platform: UNKNOWN
Classifier: Development Status :: 1 - Planning
Classifier: Environment :: Console
Classifier: Environment :: Plugins
Classifier: Intended Audience :: Developers
Classifier: Intended Audience :: End Users/Desktop
Classifier: Natural Language :: English
Classifier: License :: OSI Approved :: Apache Software License
Classifier: Programming Language :: Python
Classifier: Programming Language :: Python :: 3 :: Only
Classifier: Programming Language :: Python :: 3.6
Classifier: Programming Language :: Python :: 3.7
Classifier: Programming Language :: Python :: Implementation :: CPython
Classifier: Topic :: Utilities
Requires-Python: >=3.6
Requires-Dist: click (>=6.7)
